micro_clean_gen-1.0.3.dist-info/licenses/LICENSE
micro_gen/__init__.py
micro_gen/cli.py
micro_gen/core/__init__.py
micro_gen/core/base_generator.py
micro_gen/core/cqrs_generator.py
micro_gen/core/crud_generator.py
micro_gen/core/deploy_generator.py
micro_gen/core/magic_enhancer.py
micro_gen/core/simple_enhancer.py
micro_gen/core/simple_generators.py
micro_gen/core/task_generator.py
micro_gen/core/utils.py
micro_gen/core/templates/log_query.sh
micro_gen/core/templates/template_loader.py
micro_gen/core/templates/cqrs/aggregate_entity.go.tmpl
micro_gen/core/templates/cqrs/command.go.tmpl
micro_gen/core/templates/cqrs/command_handler.go.tmpl
micro_gen/core/templates/cqrs/cqrs_example.go.tmpl
micro_gen/core/templates/cqrs/event.go.tmpl
micro_gen/core/templates/cqrs/projection_processor.go.tmpl
micro_gen/core/templates/cqrs/read_model.go.tmpl
micro_gen/core/templates/es/entity_event.go.tmpl
micro_gen/core/templates/es/event_bus.go.tmpl
micro_gen/core/templates/es/event_snapshot.go.tmpl
micro_gen/core/templates/es/event_store.go.tmpl
micro_gen/core/templates/es/example_usage.go.tmpl
micro_gen/core/templates/es/jetstream_bus.go.tmpl
micro_gen/core/templates/es/jetstream_store.go.tmpl
micro_gen/core/templates/es/snapshot_store.go.tmpl
micro_gen/core/templates/init/config.go.tmpl
micro_gen/core/templates/init/docker-compose.yaml.tmpl
micro_gen/core/templates/init/dockerfile.tmpl
micro_gen/core/templates/init/env.tmpl
micro_gen/core/templates/init/gitignore.tmpl
micro_gen/core/templates/init/go_mod.tmpl
micro_gen/core/templates/init/health_handler.go.tmpl
micro_gen/core/templates/init/logger.go.tmpl
micro_gen/core/templates/init/main.go.tmpl
micro_gen/core/templates/init/makefile.tmpl
micro_gen/core/templates/init/router.go.tmpl
micro_gen/core/templates/projection/aggregate_read_model.go.tmpl
micro_gen/core/templates/projection/entity_read_model.go.tmpl
micro_gen/core/templates/projection/memory_repository.go.tmpl
micro_gen/core/templates/projection/projection_example.go.tmpl
micro_clean_gen-1.0.3.dist-info/METADATA
micro_clean_gen-1.0.3.dist-info/WHEEL
micro_clean_gen-1.0.3.dist-info/entry_points.txt
micro_clean_gen-1.0.3.dist-info/top_level.txt
micro_clean_gen-1.0.3.dist-info/RECORD
